{
    "name": "FPL Summary",
    "schemaVersion": "1.4",
    "dashboard": {
        "_type": "layout/grid",
        "contents": [
            {
                "static": false,
                "w": 3,
                "moved": false,
                "h": 2,
                "x": 0,
                "y": 0,
                "i": "0269ec38-dc97-41b8-b060-4c2884721154",
                "z": 0,
                "config": {
                    "dataStream": {
                        "name": "managerInformation",
                        "dataSourceConfig": {
                            "userID": "3510322"
                        },
                        "id": "{{dataStreams.managerInformation}}",
                        "pluginConfigId": "{{configId}}"
                    },
                    "_type": "tile/data-stream",
                    "description": "",
                    "activePluginConfigIds": [
                        "{{configId}}"
                    ],
                    "title": "Manager Information",
                    "visualisation": {
                        "type": "data-stream-table",
                        "config": {
                            "data-stream-table": {
                                "hiddenColumns": [
                                    "started_event",
                                    "favourite_team",
                                    "player_region_id",
                                    "player_region_iso_code_short",
                                    "player_region_iso_code_long",
                                    "leagues.classic.0.id",
                                    "leagues.classic.0.short_name",
                                    "leagues.classic.0.created",
                                    "leagues.classic.0.closed",
                                    "leagues.classic.0.rank",
                                    "leagues.classic.0.max_entries",
                                    "leagues.classic.0.league_type",
                                    "leagues.classic.0.scoring",
                                    "leagues.classic.0.admin_entry",
                                    "leagues.classic.0.start_event",
                                    "leagues.classic.0.entry_can_leave",
                                    "leagues.classic.0.entry_can_admin",
                                    "leagues.classic.0.entry_can_invite",
                                    "leagues.classic.0.has_cup",
                                    "leagues.classic.0.cup_league",
                                    "leagues.classic.0.cup_qualified",
                                    "leagues.classic.0.rank_count",
                                    "leagues.classic.0.entry_percentile_rank",
                                    "leagues.classic.0.active_phases.0.phase",
                                    "leagues.classic.0.active_phases.0.rank",
                                    "leagues.classic.0.active_phases.0.last_rank",
                                    "leagues.classic.0.active_phases.0.rank_sort",
                                    "leagues.classic.0.active_phases.0.total",
                                    "leagues.classic.0.active_phases.0.league_id",
                                    "leagues.classic.0.active_phases.0.rank_count",
                                    "leagues.classic.0.active_phases.0.entry_percentile_rank",
                                    "leagues.classic.0.active_phases.1.phase",
                                    "leagues.classic.0.active_phases.1.rank",
                                    "leagues.classic.0.active_phases.1.last_rank",
                                    "leagues.classic.0.active_phases.1.rank_sort",
                                    "leagues.classic.0.active_phases.1.total",
                                    "leagues.classic.0.active_phases.1.league_id",
                                    "leagues.classic.0.active_phases.1.rank_count",
                                    "leagues.classic.0.active_phases.1.entry_percentile_rank",
                                    "leagues.classic.0.entry_rank",
                                    "leagues.classic.0.entry_last_rank",
                                    "leagues.classic.1.id",
                                    "leagues.classic.1.name",
                                    "leagues.classic.1.short_name",
                                    "leagues.classic.1.created",
                                    "leagues.classic.1.closed",
                                    "leagues.classic.1.rank",
                                    "leagues.classic.1.max_entries",
                                    "leagues.classic.1.league_type",
                                    "leagues.classic.1.scoring",
                                    "leagues.classic.1.admin_entry",
                                    "leagues.classic.1.start_event",
                                    "leagues.classic.1.entry_can_leave",
                                    "leagues.classic.1.entry_can_admin",
                                    "leagues.classic.1.entry_can_invite",
                                    "leagues.classic.1.has_cup",
                                    "leagues.classic.1.cup_league",
                                    "leagues.classic.1.cup_qualified",
                                    "leagues.classic.1.rank_count",
                                    "leagues.classic.1.entry_percentile_rank",
                                    "leagues.classic.1.active_phases.0.phase",
                                    "leagues.classic.1.active_phases.0.rank",
                                    "leagues.classic.1.active_phases.0.last_rank",
                                    "leagues.classic.1.active_phases.0.rank_sort",
                                    "leagues.classic.1.active_phases.0.total",
                                    "leagues.classic.1.active_phases.0.league_id",
                                    "leagues.classic.1.active_phases.0.rank_count",
                                    "leagues.classic.1.active_phases.0.entry_percentile_rank",
                                    "leagues.classic.1.active_phases.1.phase",
                                    "leagues.classic.1.active_phases.1.rank",
                                    "leagues.classic.1.active_phases.1.last_rank",
                                    "leagues.classic.1.active_phases.1.rank_sort",
                                    "leagues.classic.1.active_phases.1.total",
                                    "leagues.classic.1.active_phases.1.league_id",
                                    "leagues.classic.1.active_phases.1.rank_count",
                                    "leagues.classic.1.active_phases.1.entry_percentile_rank",
                                    "leagues.classic.1.entry_rank",
                                    "leagues.classic.1.entry_last_rank",
                                    "leagues.classic.2.id",
                                    "leagues.classic.2.name",
                                    "leagues.classic.2.short_name",
                                    "leagues.classic.2.created",
                                    "leagues.classic.2.closed",
                                    "leagues.classic.2.rank",
                                    "leagues.classic.2.max_entries",
                                    "leagues.classic.2.league_type",
                                    "leagues.classic.2.scoring",
                                    "leagues.classic.2.admin_entry",
                                    "leagues.classic.2.start_event",
                                    "leagues.classic.2.entry_can_leave",
                                    "leagues.classic.2.entry_can_admin",
                                    "leagues.classic.2.entry_can_invite",
                                    "leagues.classic.2.has_cup",
                                    "leagues.classic.2.cup_league",
                                    "leagues.classic.2.cup_qualified",
                                    "leagues.classic.2.rank_count",
                                    "leagues.classic.2.entry_percentile_rank",
                                    "leagues.classic.2.active_phases.0.phase",
                                    "leagues.classic.2.active_phases.0.rank",
                                    "leagues.classic.2.active_phases.0.last_rank",
                                    "leagues.classic.2.active_phases.0.rank_sort",
                                    "leagues.classic.2.active_phases.0.total",
                                    "leagues.classic.2.active_phases.0.league_id",
                                    "leagues.classic.2.active_phases.0.rank_count",
                                    "leagues.classic.2.active_phases.0.entry_percentile_rank",
                                    "leagues.classic.2.active_phases.1.phase",
                                    "leagues.classic.2.active_phases.1.rank",
                                    "leagues.classic.2.active_phases.1.last_rank",
                                    "leagues.classic.2.active_phases.1.rank_sort",
                                    "leagues.classic.2.active_phases.1.total",
                                    "leagues.classic.2.active_phases.1.league_id",
                                    "leagues.classic.2.active_phases.1.rank_count",
                                    "leagues.classic.2.active_phases.1.entry_percentile_rank",
                                    "leagues.classic.2.entry_rank",
                                    "leagues.classic.2.entry_last_rank",
                                    "leagues.classic.3.id",
                                    "leagues.classic.3.name",
                                    "leagues.classic.3.short_name",
                                    "leagues.classic.3.created",
                                    "leagues.classic.3.closed",
                                    "leagues.classic.3.rank",
                                    "leagues.classic.3.max_entries",
                                    "leagues.classic.3.league_type",
                                    "leagues.classic.3.scoring",
                                    "leagues.classic.3.admin_entry",
                                    "leagues.classic.3.start_event",
                                    "leagues.classic.3.entry_can_leave",
                                    "leagues.classic.3.entry_can_admin",
                                    "leagues.classic.3.entry_can_invite",
                                    "leagues.classic.3.has_cup",
                                    "leagues.classic.3.cup_league",
                                    "leagues.classic.3.cup_qualified",
                                    "leagues.classic.3.rank_count",
                                    "leagues.classic.3.entry_percentile_rank",
                                    "leagues.classic.3.active_phases.0.phase",
                                    "leagues.classic.3.active_phases.0.rank",
                                    "leagues.classic.3.active_phases.0.last_rank",
                                    "leagues.classic.3.active_phases.0.rank_sort",
                                    "leagues.classic.3.active_phases.0.total",
                                    "leagues.classic.3.active_phases.0.league_id",
                                    "leagues.classic.3.active_phases.0.rank_count",
                                    "leagues.classic.3.active_phases.0.entry_percentile_rank",
                                    "leagues.classic.3.active_phases.1.phase",
                                    "leagues.classic.3.active_phases.1.rank",
                                    "leagues.classic.3.active_phases.1.last_rank",
                                    "leagues.classic.3.active_phases.1.rank_sort",
                                    "leagues.classic.3.active_phases.1.total",
                                    "leagues.classic.3.active_phases.1.league_id",
                                    "leagues.classic.3.active_phases.1.rank_count",
                                    "leagues.classic.3.active_phases.1.entry_percentile_rank",
                                    "leagues.classic.3.entry_rank",
                                    "leagues.classic.3.entry_last_rank",
                                    "leagues.classic.4.id",
                                    "leagues.classic.4.name",
                                    "leagues.classic.4.short_name",
                                    "leagues.classic.4.created",
                                    "leagues.classic.4.closed",
                                    "leagues.classic.4.rank",
                                    "leagues.classic.4.max_entries",
                                    "leagues.classic.4.league_type",
                                    "leagues.classic.4.scoring",
                                    "leagues.classic.4.admin_entry",
                                    "leagues.classic.4.start_event",
                                    "leagues.classic.4.entry_can_leave",
                                    "leagues.classic.4.entry_can_admin",
                                    "leagues.classic.4.entry_can_invite",
                                    "leagues.classic.4.has_cup",
                                    "leagues.classic.4.cup_league",
                                    "leagues.classic.4.cup_qualified",
                                    "leagues.classic.4.rank_count",
                                    "leagues.classic.4.entry_percentile_rank",
                                    "leagues.classic.4.active_phases.0.phase",
                                    "leagues.classic.4.active_phases.0.rank",
                                    "leagues.classic.4.active_phases.0.last_rank",
                                    "leagues.classic.4.active_phases.0.rank_sort",
                                    "leagues.classic.4.active_phases.0.total",
                                    "leagues.classic.4.active_phases.0.league_id",
                                    "leagues.classic.4.active_phases.0.rank_count",
                                    "leagues.classic.4.active_phases.0.entry_percentile_rank",
                                    "leagues.classic.4.active_phases.1.phase",
                                    "leagues.classic.4.active_phases.1.rank",
                                    "leagues.classic.4.active_phases.1.last_rank",
                                    "leagues.classic.4.active_phases.1.rank_sort",
                                    "leagues.classic.4.active_phases.1.total",
                                    "leagues.classic.4.active_phases.1.league_id",
                                    "leagues.classic.4.active_phases.1.rank_count",
                                    "leagues.classic.4.active_phases.1.entry_percentile_rank",
                                    "leagues.classic.4.entry_rank",
                                    "leagues.classic.4.entry_last_rank",
                                    "leagues.classic.5.id",
                                    "leagues.classic.5.name",
                                    "leagues.classic.5.short_name",
                                    "leagues.classic.5.created",
                                    "leagues.classic.5.closed",
                                    "leagues.classic.5.rank",
                                    "leagues.classic.5.max_entries",
                                    "leagues.classic.5.league_type",
                                    "leagues.classic.5.scoring",
                                    "leagues.classic.5.admin_entry",
                                    "leagues.classic.5.start_event",
                                    "leagues.classic.5.entry_can_leave",
                                    "leagues.classic.5.entry_can_admin",
                                    "leagues.classic.5.entry_can_invite",
                                    "leagues.classic.5.has_cup",
                                    "leagues.classic.5.cup_league",
                                    "leagues.classic.5.cup_qualified",
                                    "leagues.classic.5.rank_count",
                                    "leagues.classic.5.entry_percentile_rank",
                                    "leagues.classic.5.active_phases.0.phase",
                                    "leagues.classic.5.active_phases.0.rank",
                                    "leagues.classic.5.active_phases.0.last_rank",
                                    "leagues.classic.5.active_phases.0.rank_sort",
                                    "leagues.classic.5.active_phases.0.total",
                                    "leagues.classic.5.active_phases.0.league_id",
                                    "leagues.classic.5.active_phases.0.rank_count",
                                    "leagues.classic.5.active_phases.0.entry_percentile_rank",
                                    "leagues.classic.5.active_phases.1.phase",
                                    "leagues.classic.5.active_phases.1.rank",
                                    "leagues.classic.5.active_phases.1.last_rank",
                                    "leagues.classic.5.active_phases.1.rank_sort",
                                    "leagues.classic.5.active_phases.1.total",
                                    "leagues.classic.5.active_phases.1.league_id",
                                    "leagues.classic.5.active_phases.1.rank_count",
                                    "leagues.classic.5.active_phases.1.entry_percentile_rank",
                                    "leagues.classic.5.entry_rank",
                                    "leagues.classic.5.entry_last_rank",
                                    "leagues.classic.6.id",
                                    "leagues.classic.6.name",
                                    "leagues.classic.6.short_name",
                                    "leagues.classic.6.created",
                                    "leagues.classic.6.closed",
                                    "leagues.classic.6.rank",
                                    "leagues.classic.6.max_entries",
                                    "leagues.classic.6.league_type",
                                    "leagues.classic.6.scoring",
                                    "leagues.classic.6.admin_entry",
                                    "leagues.classic.6.start_event",
                                    "leagues.classic.6.entry_can_leave",
                                    "leagues.classic.6.entry_can_admin",
                                    "leagues.classic.6.entry_can_invite",
                                    "leagues.classic.6.has_cup",
                                    "leagues.classic.6.cup_league",
                                    "leagues.classic.6.cup_qualified",
                                    "leagues.classic.6.rank_count",
                                    "leagues.classic.6.entry_percentile_rank",
                                    "leagues.classic.6.active_phases.0.phase",
                                    "leagues.classic.6.active_phases.0.rank",
                                    "leagues.classic.6.active_phases.0.last_rank",
                                    "leagues.classic.6.active_phases.0.rank_sort",
                                    "leagues.classic.6.active_phases.0.total",
                                    "leagues.classic.6.active_phases.0.league_id",
                                    "leagues.classic.6.active_phases.0.rank_count",
                                    "leagues.classic.6.active_phases.0.entry_percentile_rank",
                                    "leagues.classic.6.active_phases.1.phase",
                                    "leagues.classic.6.active_phases.1.rank",
                                    "leagues.classic.6.active_phases.1.last_rank",
                                    "leagues.classic.6.active_phases.1.rank_sort",
                                    "leagues.classic.6.active_phases.1.total",
                                    "leagues.classic.6.active_phases.1.league_id",
                                    "leagues.classic.6.active_phases.1.rank_count",
                                    "leagues.classic.6.active_phases.1.entry_percentile_rank",
                                    "leagues.classic.6.entry_rank",
                                    "leagues.classic.6.entry_last_rank",
                                    "leagues.classic.7.id",
                                    "leagues.classic.7.name",
                                    "leagues.classic.7.short_name",
                                    "leagues.classic.7.created",
                                    "leagues.classic.7.closed",
                                    "leagues.classic.7.rank",
                                    "leagues.classic.7.max_entries",
                                    "leagues.classic.7.league_type",
                                    "leagues.classic.7.scoring",
                                    "leagues.classic.7.admin_entry",
                                    "leagues.classic.7.start_event",
                                    "leagues.classic.7.entry_can_leave",
                                    "leagues.classic.7.entry_can_admin",
                                    "leagues.classic.7.entry_can_invite",
                                    "leagues.classic.7.has_cup",
                                    "leagues.classic.7.cup_league",
                                    "leagues.classic.7.cup_qualified",
                                    "leagues.classic.7.rank_count",
                                    "leagues.classic.7.entry_percentile_rank",
                                    "leagues.classic.7.active_phases.0.phase",
                                    "leagues.classic.7.active_phases.0.rank",
                                    "leagues.classic.7.active_phases.0.last_rank",
                                    "leagues.classic.7.active_phases.0.rank_sort",
                                    "leagues.classic.7.active_phases.0.total",
                                    "leagues.classic.7.active_phases.0.league_id",
                                    "leagues.classic.7.active_phases.0.rank_count",
                                    "leagues.classic.7.active_phases.0.entry_percentile_rank",
                                    "leagues.classic.7.active_phases.1.phase",
                                    "leagues.classic.7.active_phases.1.rank",
                                    "leagues.classic.7.active_phases.1.last_rank",
                                    "leagues.classic.7.active_phases.1.rank_sort",
                                    "leagues.classic.7.active_phases.1.total",
                                    "leagues.classic.7.active_phases.1.league_id",
                                    "leagues.classic.7.active_phases.1.rank_count",
                                    "leagues.classic.7.active_phases.1.entry_percentile_rank",
                                    "leagues.classic.7.entry_rank",
                                    "leagues.classic.7.entry_last_rank",
                                    "leagues.classic.8.id",
                                    "leagues.classic.8.name",
                                    "leagues.classic.8.short_name",
                                    "leagues.classic.8.created",
                                    "leagues.classic.8.closed",
                                    "leagues.classic.8.rank",
                                    "leagues.classic.8.max_entries",
                                    "leagues.classic.8.league_type",
                                    "leagues.classic.8.scoring",
                                    "leagues.classic.8.admin_entry",
                                    "leagues.classic.8.start_event",
                                    "leagues.classic.8.entry_can_leave",
                                    "leagues.classic.8.entry_can_admin",
                                    "leagues.classic.8.entry_can_invite",
                                    "leagues.classic.8.has_cup",
                                    "leagues.classic.8.cup_league",
                                    "leagues.classic.8.cup_qualified",
                                    "leagues.classic.8.rank_count",
                                    "leagues.classic.8.entry_percentile_rank",
                                    "leagues.classic.8.active_phases.0.phase",
                                    "leagues.classic.8.active_phases.0.rank",
                                    "leagues.classic.8.active_phases.0.last_rank",
                                    "leagues.classic.8.active_phases.0.rank_sort",
                                    "leagues.classic.8.active_phases.0.total",
                                    "leagues.classic.8.active_phases.0.league_id",
                                    "leagues.classic.8.active_phases.0.rank_count",
                                    "leagues.classic.8.active_phases.0.entry_percentile_rank",
                                    "leagues.classic.8.active_phases.1.phase",
                                    "leagues.classic.8.active_phases.1.rank",
                                    "leagues.classic.8.active_phases.1.last_rank",
                                    "leagues.classic.8.active_phases.1.rank_sort",
                                    "leagues.classic.8.active_phases.1.total",
                                    "leagues.classic.8.active_phases.1.league_id",
                                    "leagues.classic.8.active_phases.1.rank_count",
                                    "leagues.classic.8.active_phases.1.entry_percentile_rank",
                                    "leagues.classic.8.entry_rank",
                                    "leagues.classic.8.entry_last_rank",
                                    "leagues.classic.9.id",
                                    "leagues.classic.9.name",
                                    "leagues.classic.9.short_name",
                                    "leagues.classic.9.created",
                                    "leagues.classic.9.closed",
                                    "leagues.classic.9.rank",
                                    "leagues.classic.9.max_entries",
                                    "leagues.classic.9.league_type",
                                    "leagues.classic.9.scoring",
                                    "leagues.classic.9.admin_entry",
                                    "leagues.classic.9.start_event",
                                    "leagues.classic.9.entry_can_leave",
                                    "leagues.classic.9.entry_can_admin",
                                    "leagues.classic.9.entry_can_invite",
                                    "leagues.classic.9.has_cup",
                                    "leagues.classic.9.cup_league",
                                    "leagues.classic.9.cup_qualified",
                                    "leagues.classic.9.rank_count",
                                    "leagues.classic.9.entry_percentile_rank",
                                    "leagues.classic.9.active_phases.0.phase",
                                    "leagues.classic.9.active_phases.0.rank",
                                    "leagues.classic.9.active_phases.0.last_rank",
                                    "leagues.classic.9.active_phases.0.rank_sort",
                                    "leagues.classic.9.active_phases.0.total",
                                    "leagues.classic.9.active_phases.0.league_id",
                                    "leagues.classic.9.active_phases.0.rank_count",
                                    "leagues.classic.9.active_phases.0.entry_percentile_rank",
                                    "leagues.classic.9.active_phases.1.phase",
                                    "leagues.classic.9.active_phases.1.rank",
                                    "leagues.classic.9.active_phases.1.last_rank",
                                    "leagues.classic.9.active_phases.1.rank_sort",
                                    "leagues.classic.9.active_phases.1.total",
                                    "leagues.classic.9.active_phases.1.league_id",
                                    "leagues.classic.9.active_phases.1.rank_count",
                                    "leagues.classic.9.active_phases.1.entry_percentile_rank",
                                    "leagues.classic.9.entry_rank",
                                    "leagues.classic.9.entry_last_rank",
                                    "leagues.classic.10.id",
                                    "leagues.classic.10.name",
                                    "leagues.classic.10.short_name",
                                    "leagues.classic.10.created",
                                    "leagues.classic.10.closed",
                                    "leagues.classic.10.rank",
                                    "leagues.classic.10.max_entries",
                                    "leagues.classic.10.league_type",
                                    "leagues.classic.10.scoring",
                                    "leagues.classic.10.admin_entry",
                                    "leagues.classic.10.start_event",
                                    "leagues.classic.10.entry_can_leave",
                                    "leagues.classic.10.entry_can_admin",
                                    "leagues.classic.10.entry_can_invite",
                                    "leagues.classic.10.has_cup",
                                    "leagues.classic.10.cup_league",
                                    "leagues.classic.10.cup_qualified",
                                    "leagues.classic.10.rank_count",
                                    "leagues.classic.10.entry_percentile_rank",
                                    "leagues.classic.10.active_phases.0.phase",
                                    "leagues.classic.10.active_phases.0.rank",
                                    "leagues.classic.10.active_phases.0.last_rank",
                                    "leagues.classic.10.active_phases.0.rank_sort",
                                    "leagues.classic.10.active_phases.0.total",
                                    "leagues.classic.10.active_phases.0.league_id",
                                    "leagues.classic.10.active_phases.0.rank_count",
                                    "leagues.classic.10.active_phases.0.entry_percentile_rank",
                                    "leagues.classic.10.active_phases.1.phase",
                                    "leagues.classic.10.active_phases.1.rank",
                                    "leagues.classic.10.active_phases.1.last_rank",
                                    "leagues.classic.10.active_phases.1.rank_sort",
                                    "leagues.classic.10.active_phases.1.total",
                                    "leagues.classic.10.active_phases.1.league_id",
                                    "leagues.classic.10.active_phases.1.rank_count",
                                    "leagues.classic.10.active_phases.1.entry_percentile_rank",
                                    "leagues.classic.10.entry_rank",
                                    "leagues.classic.10.entry_last_rank",
                                    "leagues.classic.11.id",
                                    "leagues.classic.11.name",
                                    "leagues.classic.11.short_name",
                                    "leagues.classic.11.created",
                                    "leagues.classic.11.closed",
                                    "leagues.classic.11.rank",
                                    "leagues.classic.11.max_entries",
                                    "leagues.classic.11.league_type",
                                    "leagues.classic.11.scoring",
                                    "leagues.classic.11.admin_entry",
                                    "leagues.classic.11.start_event",
                                    "leagues.classic.11.entry_can_leave",
                                    "leagues.classic.11.entry_can_admin",
                                    "leagues.classic.11.entry_can_invite",
                                    "leagues.classic.11.has_cup",
                                    "leagues.classic.11.cup_league",
                                    "leagues.classic.11.cup_qualified",
                                    "leagues.classic.11.rank_count",
                                    "leagues.classic.11.entry_percentile_rank",
                                    "leagues.classic.11.active_phases.0.phase",
                                    "leagues.classic.11.active_phases.0.rank",
                                    "leagues.classic.11.active_phases.0.last_rank",
                                    "leagues.classic.11.active_phases.0.rank_sort",
                                    "leagues.classic.11.active_phases.0.total",
                                    "leagues.classic.11.active_phases.0.league_id",
                                    "leagues.classic.11.active_phases.0.rank_count",
                                    "leagues.classic.11.active_phases.0.entry_percentile_rank",
                                    "leagues.classic.11.active_phases.1.phase",
                                    "leagues.classic.11.active_phases.1.rank",
                                    "leagues.classic.11.active_phases.1.last_rank",
                                    "leagues.classic.11.active_phases.1.rank_sort",
                                    "leagues.classic.11.active_phases.1.total",
                                    "leagues.classic.11.active_phases.1.league_id",
                                    "leagues.classic.11.active_phases.1.rank_count",
                                    "leagues.classic.11.active_phases.1.entry_percentile_rank",
                                    "leagues.classic.11.entry_rank",
                                    "leagues.classic.11.entry_last_rank",
                                    "leagues.classic.12.id",
                                    "leagues.classic.12.name",
                                    "leagues.classic.12.short_name",
                                    "leagues.classic.12.created",
                                    "leagues.classic.12.closed",
                                    "leagues.classic.12.rank",
                                    "leagues.classic.12.max_entries",
                                    "leagues.classic.12.league_type",
                                    "leagues.classic.12.scoring",
                                    "leagues.classic.12.admin_entry",
                                    "leagues.classic.12.start_event",
                                    "leagues.classic.12.entry_can_leave",
                                    "leagues.classic.12.entry_can_admin",
                                    "leagues.classic.12.entry_can_invite",
                                    "leagues.classic.12.has_cup",
                                    "leagues.classic.12.cup_league",
                                    "leagues.classic.12.cup_qualified",
                                    "leagues.classic.12.rank_count",
                                    "leagues.classic.12.entry_percentile_rank",
                                    "leagues.classic.12.active_phases.0.phase",
                                    "leagues.classic.12.active_phases.0.rank",
                                    "leagues.classic.12.active_phases.0.last_rank",
                                    "leagues.classic.12.active_phases.0.rank_sort",
                                    "leagues.classic.12.active_phases.0.total",
                                    "leagues.classic.12.active_phases.0.league_id",
                                    "leagues.classic.12.active_phases.0.rank_count",
                                    "leagues.classic.12.active_phases.0.entry_percentile_rank",
                                    "leagues.classic.12.active_phases.1.phase",
                                    "leagues.classic.12.active_phases.1.rank",
                                    "leagues.classic.12.active_phases.1.last_rank",
                                    "leagues.classic.12.active_phases.1.rank_sort",
                                    "leagues.classic.12.active_phases.1.total",
                                    "leagues.classic.12.active_phases.1.league_id",
                                    "leagues.classic.12.active_phases.1.rank_count",
                                    "leagues.classic.12.active_phases.1.entry_percentile_rank",
                                    "leagues.classic.12.entry_rank",
                                    "leagues.classic.12.entry_last_rank",
                                    "leagues.classic.13.id",
                                    "leagues.classic.13.name",
                                    "leagues.classic.13.short_name",
                                    "leagues.classic.13.created",
                                    "leagues.classic.13.closed",
                                    "leagues.classic.13.rank",
                                    "leagues.classic.13.max_entries",
                                    "leagues.classic.13.league_type",
                                    "leagues.classic.13.scoring",
                                    "leagues.classic.13.admin_entry",
                                    "leagues.classic.13.start_event",
                                    "leagues.classic.13.entry_can_leave",
                                    "leagues.classic.13.entry_can_admin",
                                    "leagues.classic.13.entry_can_invite",
                                    "leagues.classic.13.has_cup",
                                    "leagues.classic.13.cup_league",
                                    "leagues.classic.13.cup_qualified",
                                    "leagues.classic.13.rank_count",
                                    "leagues.classic.13.entry_percentile_rank",
                                    "leagues.classic.13.active_phases.0.phase",
                                    "leagues.classic.13.active_phases.0.rank",
                                    "leagues.classic.13.active_phases.0.last_rank",
                                    "leagues.classic.13.active_phases.0.rank_sort",
                                    "leagues.classic.13.active_phases.0.total",
                                    "leagues.classic.13.active_phases.0.league_id",
                                    "leagues.classic.13.active_phases.0.rank_count",
                                    "leagues.classic.13.active_phases.0.entry_percentile_rank",
                                    "leagues.classic.13.active_phases.1.phase",
                                    "leagues.classic.13.active_phases.1.rank",
                                    "leagues.classic.13.active_phases.1.last_rank",
                                    "leagues.classic.13.active_phases.1.rank_sort",
                                    "leagues.classic.13.active_phases.1.total",
                                    "leagues.classic.13.active_phases.1.league_id",
                                    "leagues.classic.13.active_phases.1.rank_count",
                                    "leagues.classic.13.active_phases.1.entry_percentile_rank",
                                    "leagues.classic.13.entry_rank",
                                    "leagues.classic.13.entry_last_rank",
                                    "leagues.classic.14.id",
                                    "leagues.classic.14.name",
                                    "leagues.classic.14.short_name",
                                    "leagues.classic.14.created",
                                    "leagues.classic.14.closed",
                                    "leagues.classic.14.rank",
                                    "leagues.classic.14.max_entries",
                                    "leagues.classic.14.league_type",
                                    "leagues.classic.14.scoring",
                                    "leagues.classic.14.admin_entry",
                                    "leagues.classic.14.start_event",
                                    "leagues.classic.14.entry_can_leave",
                                    "leagues.classic.14.entry_can_admin",
                                    "leagues.classic.14.entry_can_invite",
                                    "leagues.classic.14.has_cup",
                                    "leagues.classic.14.cup_league",
                                    "leagues.classic.14.cup_qualified",
                                    "leagues.classic.14.rank_count",
                                    "leagues.classic.14.entry_percentile_rank",
                                    "leagues.classic.14.active_phases.0.phase",
                                    "leagues.classic.14.active_phases.0.rank",
                                    "leagues.classic.14.active_phases.0.last_rank",
                                    "leagues.classic.14.active_phases.0.rank_sort",
                                    "leagues.classic.14.active_phases.0.total",
                                    "leagues.classic.14.active_phases.0.league_id",
                                    "leagues.classic.14.active_phases.0.rank_count",
                                    "leagues.classic.14.active_phases.0.entry_percentile_rank",
                                    "leagues.classic.14.active_phases.1.phase",
                                    "leagues.classic.14.active_phases.1.rank",
                                    "leagues.classic.14.active_phases.1.last_rank",
                                    "leagues.classic.14.active_phases.1.rank_sort",
                                    "leagues.classic.14.active_phases.1.total",
                                    "leagues.classic.14.active_phases.1.league_id",
                                    "leagues.classic.14.active_phases.1.rank_count",
                                    "leagues.classic.14.active_phases.1.entry_percentile_rank",
                                    "leagues.classic.14.entry_rank",
                                    "leagues.classic.14.entry_last_rank",
                                    "leagues.classic.15.id",
                                    "leagues.classic.15.name",
                                    "leagues.classic.15.short_name",
                                    "leagues.classic.15.created",
                                    "leagues.classic.15.closed",
                                    "leagues.classic.15.rank",
                                    "leagues.classic.15.max_entries",
                                    "leagues.classic.15.league_type",
                                    "leagues.classic.15.scoring",
                                    "leagues.classic.15.admin_entry",
                                    "leagues.classic.15.start_event",
                                    "leagues.classic.15.entry_can_leave",
                                    "leagues.classic.15.entry_can_admin",
                                    "leagues.classic.15.entry_can_invite",
                                    "leagues.classic.15.has_cup",
                                    "leagues.classic.15.cup_league",
                                    "leagues.classic.15.cup_qualified",
                                    "leagues.classic.15.rank_count",
                                    "leagues.classic.15.entry_percentile_rank",
                                    "leagues.classic.15.active_phases.0.phase",
                                    "leagues.classic.15.active_phases.0.rank",
                                    "leagues.classic.15.active_phases.0.last_rank",
                                    "leagues.classic.15.active_phases.0.rank_sort",
                                    "leagues.classic.15.active_phases.0.total",
                                    "leagues.classic.15.active_phases.0.league_id",
                                    "leagues.classic.15.active_phases.0.rank_count",
                                    "leagues.classic.15.active_phases.0.entry_percentile_rank",
                                    "leagues.classic.15.active_phases.1.phase",
                                    "leagues.classic.15.active_phases.1.rank",
                                    "leagues.classic.15.active_phases.1.last_rank",
                                    "leagues.classic.15.active_phases.1.rank_sort",
                                    "leagues.classic.15.active_phases.1.total",
                                    "leagues.classic.15.active_phases.1.league_id",
                                    "leagues.classic.15.active_phases.1.rank_count",
                                    "leagues.classic.15.active_phases.1.entry_percentile_rank",
                                    "leagues.classic.15.entry_rank",
                                    "leagues.classic.15.entry_last_rank",
                                    "leagues.h2h.0.id",
                                    "leagues.h2h.0.name",
                                    "leagues.h2h.0.short_name",
                                    "leagues.h2h.0.created",
                                    "leagues.h2h.0.closed",
                                    "leagues.h2h.0.rank",
                                    "leagues.h2h.0.max_entries",
                                    "leagues.h2h.0.league_type",
                                    "leagues.h2h.0.scoring",
                                    "leagues.h2h.0.admin_entry",
                                    "leagues.h2h.0.start_event",
                                    "leagues.h2h.0.entry_can_leave",
                                    "leagues.h2h.0.entry_can_admin",
                                    "leagues.h2h.0.entry_can_invite",
                                    "leagues.h2h.0.has_cup",
                                    "leagues.h2h.0.cup_league",
                                    "leagues.h2h.0.cup_qualified",
                                    "leagues.h2h.0.rank_count",
                                    "leagues.h2h.0.entry_percentile_rank",
                                    "leagues.h2h.0.entry_rank",
                                    "leagues.h2h.0.entry_last_rank",
                                    "leagues.h2h.1.id",
                                    "leagues.h2h.1.name",
                                    "leagues.h2h.1.short_name",
                                    "leagues.h2h.1.created",
                                    "leagues.h2h.1.closed",
                                    "leagues.h2h.1.rank",
                                    "leagues.h2h.1.max_entries",
                                    "leagues.h2h.1.league_type",
                                    "leagues.h2h.1.scoring",
                                    "leagues.h2h.1.admin_entry",
                                    "leagues.h2h.1.start_event",
                                    "leagues.h2h.1.entry_can_leave",
                                    "leagues.h2h.1.entry_can_admin",
                                    "leagues.h2h.1.entry_can_invite",
                                    "leagues.h2h.1.has_cup",
                                    "leagues.h2h.1.cup_league",
                                    "leagues.h2h.1.cup_qualified",
                                    "leagues.h2h.1.rank_count",
                                    "leagues.h2h.1.entry_percentile_rank",
                                    "leagues.h2h.1.entry_rank",
                                    "leagues.h2h.1.entry_last_rank",
                                    "leagues.cup.status.qualification_event",
                                    "leagues.cup.status.qualification_numbers",
                                    "leagues.cup.status.qualification_rank",
                                    "leagues.cup.status.qualification_state",
                                    "leagues.cup.cup_league",
                                    "leagues.cup_matches.0.id",
                                    "leagues.cup_matches.0.entry_1_entry",
                                    "leagues.cup_matches.0.entry_1_name",
                                    "leagues.cup_matches.0.entry_1_player_name",
                                    "leagues.cup_matches.0.entry_1_points",
                                    "leagues.cup_matches.0.entry_1_win",
                                    "leagues.cup_matches.0.entry_1_draw",
                                    "leagues.cup_matches.0.entry_1_loss",
                                    "leagues.cup_matches.0.entry_1_total",
                                    "leagues.cup_matches.0.entry_2_entry",
                                    "leagues.cup_matches.0.entry_2_name",
                                    "leagues.cup_matches.0.entry_2_player_name",
                                    "leagues.cup_matches.0.entry_2_points",
                                    "leagues.cup_matches.0.entry_2_win",
                                    "leagues.cup_matches.0.entry_2_draw",
                                    "leagues.cup_matches.0.entry_2_loss",
                                    "leagues.cup_matches.0.entry_2_total",
                                    "leagues.cup_matches.0.is_knockout",
                                    "leagues.cup_matches.0.league",
                                    "leagues.cup_matches.0.winner",
                                    "leagues.cup_matches.0.seed_value",
                                    "leagues.cup_matches.0.event",
                                    "leagues.cup_matches.0.tiebreak",
                                    "leagues.cup_matches.0.is_bye",
                                    "leagues.cup_matches.0.knockout_name",
                                    "leagues.cup_matches.1.id",
                                    "leagues.cup_matches.1.entry_1_entry",
                                    "leagues.cup_matches.1.entry_1_name",
                                    "leagues.cup_matches.1.entry_1_player_name",
                                    "leagues.cup_matches.1.entry_1_points",
                                    "leagues.cup_matches.1.entry_1_win",
                                    "leagues.cup_matches.1.entry_1_draw",
                                    "leagues.cup_matches.1.entry_1_loss",
                                    "leagues.cup_matches.1.entry_1_total",
                                    "leagues.cup_matches.1.entry_2_entry",
                                    "leagues.cup_matches.1.entry_2_name",
                                    "leagues.cup_matches.1.entry_2_player_name",
                                    "leagues.cup_matches.1.entry_2_points",
                                    "leagues.cup_matches.1.entry_2_win",
                                    "leagues.cup_matches.1.entry_2_draw",
                                    "leagues.cup_matches.1.entry_2_loss",
                                    "leagues.cup_matches.1.entry_2_total",
                                    "leagues.cup_matches.1.is_knockout",
                                    "leagues.cup_matches.1.league",
                                    "leagues.cup_matches.1.winner",
                                    "leagues.cup_matches.1.seed_value",
                                    "leagues.cup_matches.1.event",
                                    "leagues.cup_matches.1.tiebreak",
                                    "leagues.cup_matches.1.is_bye",
                                    "leagues.cup_matches.1.knockout_name",
                                    "leagues.cup_matches.2.id",
                                    "leagues.cup_matches.2.entry_1_entry",
                                    "leagues.cup_matches.2.entry_1_name",
                                    "leagues.cup_matches.2.entry_1_player_name",
                                    "leagues.cup_matches.2.entry_1_points",
                                    "leagues.cup_matches.2.entry_1_win",
                                    "leagues.cup_matches.2.entry_1_draw",
                                    "leagues.cup_matches.2.entry_1_loss",
                                    "leagues.cup_matches.2.entry_1_total",
                                    "leagues.cup_matches.2.entry_2_entry",
                                    "leagues.cup_matches.2.entry_2_name",
                                    "leagues.cup_matches.2.entry_2_player_name",
                                    "leagues.cup_matches.2.entry_2_points",
                                    "leagues.cup_matches.2.entry_2_win",
                                    "leagues.cup_matches.2.entry_2_draw",
                                    "leagues.cup_matches.2.entry_2_loss",
                                    "leagues.cup_matches.2.entry_2_total",
                                    "leagues.cup_matches.2.is_knockout",
                                    "leagues.cup_matches.2.league",
                                    "leagues.cup_matches.2.winner",
                                    "leagues.cup_matches.2.seed_value",
                                    "leagues.cup_matches.2.event",
                                    "leagues.cup_matches.2.tiebreak",
                                    "leagues.cup_matches.2.is_bye",
                                    "leagues.cup_matches.2.knockout_name",
                                    "name",
                                    "name_change_blocked",
                                    "entered_events.0",
                                    "entered_events.1",
                                    "entered_events.2",
                                    "entered_events.3",
                                    "entered_events.4",
                                    "entered_events.5",
                                    "entered_events.6",
                                    "entered_events.7",
                                    "entered_events.8",
                                    "entered_events.9",
                                    "entered_events.10",
                                    "entered_events.11",
                                    "entered_events.12",
                                    "entered_events.13",
                                    "entered_events.14",
                                    "entered_events.15",
                                    "entered_events.16",
                                    "kit",
                                    "last_deadline_bank",
                                    "last_deadline_value",
                                    "last_deadline_total_transfers",
                                    "club_badge_src"
                                ],
                                "transpose": true,
                                "columnOrder": [
                                    "id",
                                    "player_first_name",
                                    "player_last_name",
                                    "leagues.classic.0.name",
                                    "player_region_name",
                                    "joined_time",
                                    "years_active",
                                    "summary_overall_points",
                                    "summary_overall_rank",
                                    "current_event",
                                    "summary_event_points",
                                    "summary_event_rank"
                                ],
                                "columnDisplayNames": {}
                            }
                        }
                    }
                }
            },
            {
                "static": false,
                "w": 3,
                "moved": false,
                "h": 2,
                "x": 3,
                "y": 0,
                "i": "f82014ea-6c39-49d8-85bb-09c759d0b98c",
                "z": 0,
                "config": {
                    "timeframe": "none",
                    "dataStream": {
                        "name": "managerHistory",
                        "dataSourceConfig": {
                            "userID": "3510322"
                        },
                        "id": "{{dataStreams.managerHistory}}",
                        "sort": {
                            "by": [
                                [
                                    "season_name",
                                    "desc"
                                ]
                            ]
                        },
                        "pluginConfigId": "{{configId}}"
                    },
                    "_type": "tile/data-stream",
                    "description": "All previous seasons",
                    "activePluginConfigIds": [
                        "{{configId}}"
                    ],
                    "title": "Manager History",
                    "visualisation": {
                        "type": "data-stream-table",
                        "config": {
                            "data-stream-table": {
                                "columnOrder": [
                                    "season_name",
                                    "total_points",
                                    "rank"
                                ],
                                "hiddenColumns": []
                            }
                        }
                    }
                }
            },
            {
                "static": false,
                "w": 2,
                "moved": false,
                "h": 2,
                "x": 6,
                "y": 0,
                "i": "1",
                "z": 0,
                "config": {
                    "_type": "tile/image",
                    "description": "",
                    "title": "",
                    "visualisation": {
                        "config": {
                            "title": "",
                            "src": "https://resources.premierleague.com/photos/2020/08/11/0d811107-6d08-4e1c-b9ee-17dab9d065e7/FPL-Statement-Lead.png?width=930&height=620"
                        }
                    }
                }
            },
            {
                "static": false,
                "w": 5,
                "moved": false,
                "h": 2,
                "x": 3,
                "y": 2,
                "i": "e8c567cf-74a6-480a-a028-1e2b654e5f89",
                "z": 0,
                "config": {
                    "timeframe": "none",
                    "dataStream": {
                        "name": "gameweekData",
                        "id": "{{dataStreams.gameweekData}}",
                        "pluginConfigId": "{{configId}}"
                    },
                    "_type": "tile/data-stream",
                    "description": "Static data about the current season",
                    "activePluginConfigIds": [
                        "{{configId}}"
                    ],
                    "title": "Gameweek Data",
                    "visualisation": {
                        "type": "data-stream-table",
                        "config": {
                            "data-stream-table": {
                                "columnOrder": [
                                    "id",
                                    "deadline_time",
                                    "average_entry_score",
                                    "chip_plays.0.num_played",
                                    "chip_plays.1.chip_name",
                                    "chip_plays.1.num_played",
                                    "most_transferred_in",
                                    "top_element_info.points",
                                    "transfers_made",
                                    "most_captained",
                                    "most_vice_captained",
                                    "chip_plays.2.num_played",
                                    "chip_plays.3.chip_name",
                                    "chip_plays.3.num_played",
                                    "can_enter",
                                    "can_manage",
                                    "chip_plays.0.chip_name",
                                    "chip_plays.2.chip_name",
                                    "cup_leagues_created",
                                    "data_checked",
                                    "deadline_time_epoch",
                                    "deadline_time_game_offset",
                                    "finished",
                                    "h2h_ko_matches_created",
                                    "highest_score",
                                    "highest_scoring_entry",
                                    "is_current",
                                    "is_next",
                                    "is_previous",
                                    "most_selected",
                                    "name",
                                    "overrides.pick_multiplier",
                                    "ranked_count",
                                    "release_time",
                                    "released",
                                    "top_element",
                                    "top_element_info",
                                    "top_element_info.id"
                                ],
                                "hiddenColumns": []
                            }
                        }
                    }
                }
            },
            {
                "static": false,
                "w": 3,
                "moved": false,
                "h": 2,
                "x": 0,
                "y": 2,
                "i": "ec44d240-6ac6-49f3-90c0-fd88ba75c2e7",
                "z": 0,
                "config": {
                    "timeframe": "none",
                    "dataStream": {
                        "name": "leagueSummary",
                        "dataSourceConfig": {
                            "leagueID": "708036"
                        },
                        "id": "{{dataStreams.leagueSummary}}",
                        "sort": {
                            "by": [
                                [
                                    "rank",
                                    "asc"
                                ]
                            ]
                        },
                        "pluginConfigId": "{{configId}}"
                    },
                    "_type": "tile/data-stream",
                    "description": "Saved data stream",
                    "activePluginConfigIds": [
                        "{{configId}}"
                    ],
                    "title": "League Summary",
                    "visualisation": {
                        "type": "data-stream-table",
                        "config": {
                            "data-stream-table": {
                                "columnOrder": [
                                    "rank",
                                    "entry_name",
                                    "event_total",
                                    "total",
                                    "rank[Expanded].comparedTo[last_rank].compare1"
                                ],
                                "hiddenColumns": [
                                    "rank_sort",
                                    "last_rank",
                                    "entry"
                                ]
                            }
                        }
                    }
                }
            },
            {
                "static": false,
                "w": 4,
                "moved": false,
                "h": 3,
                "x": 0,
                "y": 4,
                "i": "121a65b8-b410-40df-9208-770ae5fa1262",
                "z": 0,
                "config": {
                    "timeframe": "none",
                    "dataStream": {
                        "name": "managerSummary",
                        "dataSourceConfig": {
                            "userID": "3510322"
                        },
                        "id": "{{dataStreams.managerSummary}}",
                        "pluginConfigId": "{{configId}}"
                    },
                    "_type": "tile/data-stream",
                    "description": "This season",
                    "activePluginConfigIds": [
                        "{{configId}}"
                    ],
                    "title": "Weekly Points",
                    "visualisation": {
                        "type": "data-stream-bar-chart",
                        "config": {
                            "data-stream-bar-chart": {
                                "xAxisGroup": "none",
                                "showLegend": false,
                                "range": {
                                    "type": "auto"
                                },
                                "showGrid": true,
                                "grouping": false,
                                "xAxisData": "event",
                                "displayMode": "actual",
                                "showTotals": false,
                                "yAxisLabel": "",
                                "horizontalLayout": "vertical",
                                "showValue": false,
                                "yAxisData": [
                                    "points"
                                ],
                                "showYAxisLabel": true,
                                "xAxisLabel": "",
                                "legendPosition": "bottom",
                                "showXAxisLabel": true
                            }
                        }
                    }
                }
            },
            {
                "static": false,
                "w": 4,
                "moved": false,
                "h": 3,
                "x": 4,
                "y": 4,
                "i": "1808f062-623d-458a-a755-84cb9a00d23f",
                "z": 0,
                "config": {
                    "timeframe": "none",
                    "dataStream": {
                        "name": "managerSummary",
                        "dataSourceConfig": {
                            "userID": "3510322"
                        },
                        "id": "{{dataStreams.managerSummary}}",
                        "pluginConfigId": "{{configId}}"
                    },
                    "_type": "tile/data-stream",
                    "description": "This season",
                    "activePluginConfigIds": [
                        "{{configId}}"
                    ],
                    "title": "Overall Rank",
                    "visualisation": {
                        "type": "data-stream-line-graph",
                        "config": {
                            "data-stream-line-graph": {
                                "xAxisColumn": "event",
                                "yAxisColumn": [
                                    "overall_rank"
                                ],
                                "seriesColumn": "none"
                            }
                        }
                    }
                }
            }
        ],
        "version": 98,
        "columns": 8
    },
    "path": "fpl-summary",
    "folderPath": []
}