{
    "name": "Overview",
    "schemaVersion": "1.4",
    "dashboard": {
        "_type": "layout/grid",
        "contents": [
            {
                "static": false,
                "w": 2,
                "moved": false,
                "h": 4,
                "x": 0,
                "y": 0,
                "i": "f1c2dc6f-11e7-43e3-945d-a8b4e6f3f2d5",
                "z": 0,
                "config": {
                    "timeframe": "none",
                    "dataStream": {
                        "name": "certificateOrders",
                        "filter": {
                            "multiOperation": "and",
                            "filters": [
                                {
                                    "column": "is_renewed",
                                    "operation": "equals",
                                    "value": "false"
                                }
                            ]
                        },
                        "id": "{{dataStreams.certificateOrders}}",
                        "pluginConfigId": "{{configId}}"
                    },
                    "_type": "tile/data-stream",
                    "description": "",
                    "monitorOld": {
                        "tileRollsUp": true,
                        "monitorType": "threshold",
                        "condition": {
                            "columns": [],
                            "logic": {
                                "if": [
                                    {
                                        ">": [
                                            {
                                                "var": "count"
                                            },
                                            0
                                        ]
                                    },
                                    "error"
                                ]
                            }
                        },
                        "_type": "simple",
                        "aggregation": "count",
                        "groupBy": "__group_by_none__",
                        "frequency": 15
                    },
                    "activePluginConfigIds": ["{{configId}}"],
                    "title": "⏳ Certificates Pending Renewal",
                    "visualisation": {
                        "type": "data-stream-table",
                        "config": {
                            "data-stream-table": {
                                "columnOrder": [
                                    "organization.name",
                                    "certificate.serial_number",
                                    "product.name",
                                    "price",
                                    "certificate.valid_from",
                                    "certificate.valid_till",
                                    "certificate.days_remaining",
                                    "date_created",
                                    "has_reissues",
                                    "is_renewed",
                                    "order_valid_till",
                                    "status",
                                    "validity_years"
                                ],
                                "hiddenColumns": [
                                    "certificate.dns_names.0",
                                    "container.name",
                                    "organization.id",
                                    "number_of_sans",
                                    "reissues_count",
                                    "duplicates_count",
                                    "container.id",
                                    "certificate.id",
                                    "id",
                                    "certificate.signature_hash",
                                    "container.is_active",
                                    "disable_renewal_notifications",
                                    "has_duplicates",
                                    "product.name_id",
                                    "product.type",
                                    "product_name_id"
                                ],
                                "transpose": true
                            }
                        }
                    }
                }
            },
            {
                "static": false,
                "w": 2,
                "moved": false,
                "h": 4,
                "x": 2,
                "y": 0,
                "i": "f9061103-7839-410c-8802-bda18ad36193",
                "z": 0,
                "config": {
                    "timeframe": "none",
                    "dataStream": {
                        "name": "certificateOrders",
                        "id": "{{dataStreams.certificateOrders}}",
                        "pluginConfigId": "{{configId}}"
                    },
                    "_type": "tile/data-stream",
                    "description": "",
                    "activePluginConfigIds": ["{{configId}}"],
                    "title": "🧾 Certificate Order Cost",
                    "visualisation": {
                        "type": "data-stream-bar-chart",
                        "config": {
                            "data-stream-bar-chart": {
                                "xAxisGroup": "none",
                                "showLegend": false,
                                "range": {
                                    "type": "auto"
                                },
                                "showGrid": true,
                                "grouping": false,
                                "xAxisData": "certificate.serial_number",
                                "displayMode": "actual",
                                "showTotals": false,
                                "yAxisLabel": "",
                                "horizontalLayout": "vertical",
                                "showValue": false,
                                "yAxisData": ["price"],
                                "showYAxisLabel": true,
                                "xAxisLabel": "",
                                "legendPosition": "bottom",
                                "showXAxisLabel": true
                            }
                        }
                    }
                }
            },
            {
                "static": false,
                "w": 4,
                "moved": false,
                "h": 3,
                "x": 0,
                "y": 4,
                "i": "07018f53-b11c-4617-88a0-b7afbeafd924",
                "z": 0,
                "config": {
                    "timeframe": "none",
                    "dataStream": {
                        "name": "certificateOrders",
                        "id": "{{dataStreams.certificateOrders}}",
                        "sort": {
                            "by": [["date_created", "desc"]]
                        },
                        "group": {
                            "by": [],
                            "aggregate": []
                        },
                        "pluginConfigId": "{{configId}}"
                    },
                    "_type": "tile/data-stream",
                    "description": "",
                    "activePluginConfigIds": ["{{configId}}"],
                    "title": "📜 All Certificate Orders",
                    "visualisation": {
                        "type": "data-stream-table",
                        "config": {
                            "data-stream-table": {
                                "columnOrder": [
                                    "organization.name",
                                    "certificate.serial_number",
                                    "product.name",
                                    "certificate.valid_from",
                                    "certificate.valid_till",
                                    "certificate.days_remaining",
                                    "date_created",
                                    "is_renewed",
                                    "order_valid_till",
                                    "product.name_id",
                                    "status",
                                    "validity_years"
                                ],
                                "hiddenColumns": [
                                    "certificate.dns_names.0",
                                    "container.name",
                                    "organization.id",
                                    "number_of_sans",
                                    "price",
                                    "reissues_count",
                                    "duplicates_count",
                                    "container.id",
                                    "certificate.id",
                                    "id",
                                    "certificate.signature_hash",
                                    "container.is_active",
                                    "disable_renewal_notifications",
                                    "has_duplicates",
                                    "has_reissues",
                                    "product.type",
                                    "product_name_id"
                                ]
                            }
                        }
                    }
                }
            },
            {
                "static": false,
                "w": 2,
                "moved": false,
                "h": 4,
                "x": 2,
                "y": 7,
                "i": "e0e8661b-9aa2-4579-b17d-16b15017ba91",
                "z": 0,
                "config": {
                    "timeframe": "none",
                    "dataStream": {
                        "name": "accountUsers",
                        "id": "{{dataStreams.accountUsers}}",
                        "pluginConfigId": "{{configId}}"
                    },
                    "_type": "tile/data-stream",
                    "description": "",
                    "activePluginConfigIds": ["{{configId}}"],
                    "baseTile": "data-stream-base-tile",
                    "title": "🔐👥 Certificate Portal Users",
                    "visualisation": {
                        "type": "data-stream-table",
                        "config": {
                            "data-stream-table": {
                                "hiddenColumns": [
                                    "access_roles.0.id",
                                    "container.template_id",
                                    "container.parent_id",
                                    "container.id",
                                    "account_id",
                                    "id",
                                    "container.ekey",
                                    "container.has_logo",
                                    "container.public_id",
                                    "has_container_assignments",
                                    "type"
                                ],
                                "transpose": true,
                                "columnOrder": [
                                    "first_name",
                                    "last_name",
                                    "access_roles.0.name",
                                    "container.name",
                                    "container.is_active",
                                    "email",
                                    "last_login_date",
                                    "status",
                                    "username"
                                ],
                                "resizedColumns": {
                                    "columnWidths": {
                                        "last_name": 111
                                    }
                                }
                            }
                        }
                    }
                }
            },
            {
                "static": false,
                "w": 2,
                "moved": false,
                "h": 4,
                "x": 0,
                "y": 7,
                "i": "db4c9c48-5d39-4ab0-82f8-934fd7fa41bc",
                "z": 0,
                "config": {
                    "timeframe": "none",
                    "dataStream": {
                        "name": "accountUsers",
                        "id": "{{dataStreams.accountUsers}}",
                        "pluginConfigId": "{{configId}}"
                    },
                    "_type": "tile/data-stream",
                    "description": "",
                    "activePluginConfigIds": ["{{configId}}"],
                    "title": "👥 Roles Overview",
                    "visualisation": {
                        "type": "data-stream-donut-chart",
                        "config": {
                            "data-stream-donut-chart": {
                                "valueColumn": "builtin_count_by_label",
                                "hideCenterValue": false,
                                "showValuesAsPercentage": false,
                                "legendPosition": "right",
                                "legendMode": "table",
                                "labelColumn": "access_roles.0.name"
                            }
                        }
                    }
                }
            }
        ],
        "version": 39,
        "columns": 4
    },
    "path": "overview",
    "folderPath": []
}
